spine_segmentation/__init__.py
spine_segmentation/annotators/__init__.py
spine_segmentation/annotators/annotator_base.py
spine_segmentation/annotators/vector_annotator.py
spine_segmentation/cli/cli.py
spine_segmentation/dataloader/statistics.py
spine_segmentation/datasets/__init__.py
spine_segmentation/datasets/augmentation.py
spine_segmentation/datasets/feature_dataset.py
spine_segmentation/datasets/metadata_prediction_dataset.py
spine_segmentation/datasets/patch_segmentation_dataset.py
spine_segmentation/datasets/path_helper.py
spine_segmentation/datasets/sample.py
spine_segmentation/datasets/segmentation_dataset.py
spine_segmentation/datasets/vector_table_graphs_dataset.py
spine_segmentation/evaluate/analyze_edge_cases.py
spine_segmentation/evaluate/analyze_index_list.py
spine_segmentation/evaluate/classic_ml.py
spine_segmentation/evaluate/eval_created_stats.py
spine_segmentation/evaluate/eval_instance_seg_model.py
spine_segmentation/evaluate/eval_splitting.py
spine_segmentation/evaluate/load_model.py
spine_segmentation/evaluate/metadata.py
spine_segmentation/evaluate/volume_size_in_gt.py
spine_segmentation/inference/instance_segmentation.py
spine_segmentation/inference/onnx_model.py
spine_segmentation/instance_separation/instance_separation.py
spine_segmentation/losses/diffis1.py
spine_segmentation/model_downloader/model_downloader.py
spine_segmentation/plotting/bmi.py
spine_segmentation/plotting/classification_correlation.py
spine_segmentation/plotting/patient_metadata.py
spine_segmentation/plotting/plot_slice.py
spine_segmentation/plotting/plot_statistics.py
spine_segmentation/plotting/read_npz_eval_per_roi_accuracy.py
spine_segmentation/plotting/show_plane_splitting_3d.py
spine_segmentation/plotting/ydata_profile_report.py
spine_segmentation/resources/paths.py
spine_segmentation/resources/preloaded.py
spine_segmentation/run.py
spine_segmentation/scripts/format_results.py
spine_segmentation/scripts/split_train_val_test.py
spine_segmentation-0.3.2.dist-info/METADATA
spine_segmentation-0.3.2.dist-info/WHEEL
spine_segmentation-0.3.2.dist-info/RECORD
