Metadata-Version: 2.1
Name: spine-segmentation
Version: 0.3.2
Summary: Anatomical labeling of the spine in small field-of-view MRI scans
Author: Brutenis Gliwa
Author-email: brutenis@gmail.com
Requires-Python: >=3.8.1,<3.13.0
Classifier: Development Status :: 4 - Beta
Classifier: Intended Audience :: Developers
Classifier: Operating System :: OS Independent
Classifier: Programming Language :: Python
Classifier: Programming Language :: Python :: 3
Classifier: Programming Language :: Python :: 3.9
Classifier: Programming Language :: Python :: 3.10
Classifier: Programming Language :: Python :: 3.11
Classifier: Programming Language :: Python :: 3.12
Classifier: Programming Language :: Python :: 3.8
Classifier: Topic :: Software Development :: Libraries :: Python Modules
Classifier: Typing :: Typed
Requires-Dist: connected-components-3d (>=3.12.1,<4.0.0)
Requires-Dist: loguru (>=0.7.2,<0.8.0)
Requires-Dist: nibabel (>=5.1.0,<6.0.0)
Requires-Dist: numpy (>=1.23.0,<2.0.0)
Requires-Dist: onnxruntime (==1.17.1)
Requires-Dist: onnxruntime-gpu (==1.17.1)
Requires-Dist: pandas (<2.0)
Requires-Dist: pydicom (>=2.4.3,<3.0.0)
Requires-Dist: requests (>=2.28.0,<3.0.0)
Requires-Dist: scikit-learn (>=1.2.2,<2.0.0)
Requires-Dist: seaborn (>=0.13.0,<0.14.0)
Requires-Dist: tqdm (>=4.66.2,<5.0.0)
Requires-Dist: xxhash (>=3.4.1,<4.0.0)
